wir/VERSION
wir/__init__.py
wir/errors.py
wir/models/Sleep.py
wir/models/__init__.py
wir/request_utils.py
wir/rest_client.py
wir/utils/__init__.py
wir/utils/common.py
wir/utils/sleep.py
wir/utils.py
wir/wir.py
dta_wir_api_lib_python-0.1.0.dist-info/LICENSE
dta_wir_api_lib_python-0.1.0.dist-info/METADATA
dta_wir_api_lib_python-0.1.0.dist-info/WHEEL
dta_wir_api_lib_python-0.1.0.dist-info/RECORD
